Workbook

Sheet Income Statement
A1: Acme Corp — Consolidated Income Statement
A2: $ in millions, except per-share data · Fiscal Year 2026
B3: 46022 | C3: 46112 | D3: 46203 | E3: 46295 | F3: FY2026 | G3: FY2025 | H3: YoY
A4: Revenue | B4: 412 | C4: 438.5 | D4: 471.2 | E4: 505.9 | F4: =SUM(B4:E4) -> 1827.6 | G4: 1502 | H4: =IF(G4=0,"",F4/G4-1) -> 0.21677763
A5: Cost of revenue | B5: -168.9 | C5: -177.4 | D5: -188.5 | E5: -200.8 | F5: =SUM(B5:E5) -> -735.6 | G5: -690 | H5: =IF(G5=0,"",F5/G5-1) -> 0.066086957
A6: Gross profit | B6: =B4+B5 -> 243.1 | C6: =C4+C5 -> 261.1 | D6: =D4+D5 -> 282.7 | E6: =E4+E5 -> 305.1 | F6: =F4+F5 -> 1092 | G6: 812 | H6: =IF(G6=0,"",F6/G6-1) -> 0.34482759
A7: Gross margin | B7: =B6/B4 -> 0.59004854 | C7: =C6/C4 -> 0.595439 | D7: =D6/D4 -> 0.59995756 | E7: =E6/E4 -> 0.60308361 | F7: =F6/F4 -> 0.59750492 | G7: =G6/G4 -> 0.54061252
A8: Operating expenses
A9: Research & development | B9: -52 | C9: -55.1 | D9: -58.4 | E9: -61 | F9: =SUM(B9:E9) -> -226.5 | H9: =IF(G9=0,"",F9/G9-1)
A10: Sales & marketing | B10: -70.4 | C10: -74.2 | D10: -79.9 | E10: -84.1 | F10: =SUM(B10:E10) -> -308.6 | H10: =IF(G10=0,"",F10/G10-1)
A11: General & administrative | B11: -28.1 | C11: -29 | D11: -30.2 | E11: -31.4 | F11: =SUM(B11:E11) -> -118.7 | H11: =IF(G11=0,"",F11/G11-1)
A12: Total operating expenses | B12: =SUM(B9:B11) -> -150.5 | C12: =SUM(C9:C11) -> -158.3 | D12: =SUM(D9:D11) -> -168.5 | E12: =SUM(E9:E11) -> -176.5 | F12: =SUM(F9:F11) -> -653.8 | G12: -905 | H12: =IF(G12=0,"",F12/G12-1) -> -0.27756906
A13: Operating income (EBIT) | B13: =B6+B12 -> 92.6 | C13: =C6+C12 -> 102.8 | D13: =D6+D12 -> 114.2 | E13: =E6+E12 -> 128.6 | F13: =F6+F12 -> 438.2 | G13: 412 | H13: =IF(G13=0,"",F13/G13-1) -> 0.063592233
A14: Operating margin | B14: =B13/B4 -> 0.22475728 | C14: =C13/C4 -> 0.23443558 | D14: =D13/D4 -> 0.24235993 | E14: =E13/E4 -> 0.25420043 | F14: =F13/F4 -> 0.239768 | G14: =G13/G4 -> 0.27430093
A15: Interest expense | B15: -6.2 | C15: -6.2 | D15: -6.1 | E15: -6 | F15: =SUM(B15:E15) -> -24.5 | H15: =IF(G15=0,"",F15/G15-1)
A16: Pretax income | B16: =B13+B15 -> 86.4 | C16: =C13+C15 -> 96.6 | D16: =D13+D15 -> 108.1 | E16: =E13+E15 -> 122.6 | F16: =F13+F15 -> 413.7 | G16: 387.3 | H16: =IF(G16=0,"",F16/G16-1) -> 0.068164214
A17: Income tax expense | B17: =-B16*Assumptions!$B$4 -> -51.6672 | C17: =-C16*Assumptions!$B$4 -> -57.7668 | D17: =-D16*Assumptions!$B$4 -> -64.6438 | E17: =-E16*Assumptions!$B$4 -> -73.3148 | F17: =-F16*Assumptions!$B$4 -> -247.3926 | G17: -81.333 | H17: =IF(G17=0,"",F17/G17-1) -> 2.0417248
A18: Net income | B18: =B16+B17 -> 34.7328 | C18: =C16+C17 -> 38.8332 | D18: =D16+D17 -> 43.4562 | E18: =E16+E17 -> 49.2852 | F18: =F16+F17 -> 166.3074 | G18: 300 | H18: =IF(G18=0,"",F18/G18-1) -> -0.445642
A20: Diluted EPS | B20: =B18/Assumptions!$B$5 -> 165.39429 | C20: =C18/Assumptions!$B$5 -> 184.92 | D20: =D18/Assumptions!$B$5 -> 206.93429 | E20: =E18/Assumptions!$B$5 -> 234.69143 | F20: =F18/Assumptions!$B$5 -> 791.94 | G20: =G18/Assumptions!$B$5 -> 1428.5714
A21: Revenue / EBIT (x) | F21: =F4/F13 -> 4.1706983 | G21: =FALSE() -> 0
A23: Note: Q1 begins the fiscal year on 1 Oct 2025. Tax rate and diluted share count are driven from the Assumptions tab; FY2025 shown for comparison. Figures may not foot due to rounding.

Sheet Assumptions
A1: Model Assumptions & Drivers
A2: Driver | B2: Value | C2: Comment
A3: Revenue growth (YoY) | B3: 0.208 | C3: Blended across segments
A4: Target gross margin | B4: 0.598 | C4: Mix shift to software
A5: Effective tax rate | B5: 0.21 | C5: US statutory + state
A6: Diluted shares (M) | B6: 210 | C6: Post buyback
A7: WACC | B7: 0.092 | C7: CAPM, 1.15 beta
A8: Terminal growth | B8: 0.025 | C8: Long-run GDP

Sheet Summary
B2: FY2026 Performance Summary
B3: Pulled live from the Income Statement tab
B5: Revenue | C5: Net income | D5: Gross margin | E5: Diluted EPS
B6: ='Income Statement'!F4 -> 1827.6 | C6: ='Income Statement'!F18 -> 166.3074 | D6: ='Income Statement'!F6/'Income Statement'!F4 -> 0.59750492 | E6: ='Income Statement'!F20 -> 791.94
B9: Quarterly revenue ($M) — heat-shaded
C10: Q1 | D10: Q2 | E10: Q3 | F10: Q4
B11: Revenue | C11: ='Income Statement'!B4 -> 412 | D11: ='Income Statement'!C4 -> 438.5 | E11: ='Income Statement'!D4 -> 471.2 | F11: ='Income Statement'!E4 -> 505.9
