Workbook

Sheet Assumptions
A1: Assumptions
A3: Opening revenue | B3: 1200
A4: Growth rate | B4: 0.085
A5: Gross margin | B5: 0.62
A6: Opex ratio | B6: 0.34
A7: Tax rate | B7: 0.23
A8: Discount rate | B8: 0.11
A9: Start date | B9: 46023

Sheet Model
A1: Five-year model
A3: Line | B3: =EOMONTH(Assumptions!$B$9,12) | C3: =EOMONTH(Assumptions!$B$9,24) | D3: =EOMONTH(Assumptions!$B$9,36) | E3: =EOMONTH(Assumptions!$B$9,48) | F3: =EOMONTH(Assumptions!$B$9,60)
A4: Revenue | B4: =Assumptions!$B$3*(1+Assumptions!$B$4) | C4: =B4*(1+Assumptions!$B$4) | D4: =C4*(1+Assumptions!$B$4) | E4: =D4*(1+Assumptions!$B$4) | F4: =E4*(1+Assumptions!$B$4)
A5: Gross profit | B5: =ROUND(B4*Assumptions!$B$5,1) | C5: =ROUND(C4*Assumptions!$B$5,1) | D5: =ROUND(D4*Assumptions!$B$5,1) | E5: =ROUND(E4*Assumptions!$B$5,1) | F5: =ROUND(F4*Assumptions!$B$5,1)
A6: Operating expenses | B6: =-ROUND(B4*Assumptions!$B$6,1) | C6: =-ROUND(C4*Assumptions!$B$6,1) | D6: =-ROUND(D4*Assumptions!$B$6,1) | E6: =-ROUND(E4*Assumptions!$B$6,1) | F6: =-ROUND(F4*Assumptions!$B$6,1)
A7: EBIT | B7: =SUM(B5:B6) | C7: =SUM(C5:C6) | D7: =SUM(D5:D6) | E7: =SUM(E5:E6) | F7: =SUM(F5:F6)
A8: Tax | B8: =-MAX(0,B7*Assumptions!$B$7) | C8: =-MAX(0,C7*Assumptions!$B$7) | D8: =-MAX(0,D7*Assumptions!$B$7) | E8: =-MAX(0,E7*Assumptions!$B$7) | F8: =-MAX(0,F7*Assumptions!$B$7)
A9: Net income | B9: =B7+B8 | C9: =C7+C8 | D9: =D7+D8 | E9: =E7+E8 | F9: =F7+F8
A10: Margin | B10: =IF(B4=0,"",B9/B4) | C10: =IF(C4=0,"",C9/C4) | D10: =IF(D4=0,"",D9/D4) | E10: =IF(E4=0,"",E9/E4) | F10: =IF(F4=0,"",F9/F4)
A11: Growth | B11: ="" | C11: =C4/B4-1 | D11: =D4/C4-1 | E11: =E4/D4-1 | F11: =F4/E4-1

Sheet Summary
A1: Summary
A3: Total revenue | B3: =SUM(Model!B4:F4)
A4: Total net income | B4: =SUM(Model!B9:F9)
A5: Average margin | B5: =AVERAGE(Model!B10:F10)
A6: Best year | B6: =MAX(Model!B9:F9)
A7: NPV of net income | B7: =NPV(Assumptions!B8,Model!B9:F9)
A8: Years to double | B8: =PDURATION(Assumptions!B4,1,2)
A9: Payback year | B9: =IFERROR(MATCH(TRUE,INDEX(Model!B9:F9>0,0),0),"never")
A10: Revenue over 1,500 | B10: =COUNTIF(Model!B4:F4,">1500")
A11: Weighted revenue | B11: =SUMPRODUCT(Model!B4:F4,Model!B10:F10)
A12: Label | B12: ="Model through "&TEXT(Model!F3,"yyyy")
